{
    "version": "2.0.5",
    "description": "阅读器",
    "homepage": "https://github.com/troyeguo/koodo-reader",
    "license": "MIT",
    "architecture": {
        "64bit": {
            "url": "https://github.com/troyeguo/koodo-reader/releases/download/v2.0.5/Koodo-Reader-2.0.5-x64-Win.zip",
            "hash": "8bfb37d74beebcf773b49b286d8a906743d714c13272a3c015604ad808b99490"
        }
    },
    "bin": [
        [
            "Koodo Reader.exe",
            "koodo"
        ]
    ],
    "shortcuts": [
        [
            "Koodo Reader.exe",
            "koodo"
        ]
    ],
    "persist": "data",
    "checkver": "github",
    "autoupdate": {
        "architecture": {
            "64bit": {
                "url": "https://github.com/troyeguo/koodo-reader/releases/download/v$version/Koodo-Reader-$version-x64-Win.zip"
            }
        }
    }
}
